simple_mediator/__init__.py
simple_mediator/py.typed
simple_mediator-0.1.8.dist-info/METADATA
simple_mediator-0.1.8.dist-info/WHEEL
simple_mediator-0.1.8.dist-info/licenses/LICENSE
simple_mediator-0.1.8.dist-info/RECORD
